web_render/__init__.py
web_render/interface.py
web_render/tool.py
web_render/base/__init__.py
web_render/base/__main__.py
web_render/base/abstract.py
web_render/base/extends.py
w_render-0.3.1.dist-info/METADATA
w_render-0.3.1.dist-info/WHEEL
w_render-0.3.1.dist-info/top_level.txt
w_render-0.3.1.dist-info/RECORD
