Metadata-Version: 2.1
Name: w-render
Version: 0.3.1
Summary: Render a dynamical sites.
Author: Andrey Plugin
Author-email: 9keepa@gmail.com
License: MIT
Requires-Python: >=3.8
Requires-Dist: selenium
Requires-Dist: webdriver-manager
Requires-Dist: undetected-chromedriver
Requires-Dist: python-dotenv
